mototli/__init__.py
mototli/__main__.py
mototli/client/__init__.py
mototli/client/protocol.py
mototli/client/session.py
mototli/content/__init__.py
mototli/content/attributes.py
mototli/content/directory.py
mototli/protocol/__init__.py
mototli/protocol/attributes.py
mototli/protocol/constants.py
mototli/protocol/item_types.py
mototli/protocol/request.py
mototli/protocol/response.py
mototli/py.typed
mototli/server/__init__.py
mototli/server/cgi.py
mototli/server/config.py
mototli/server/handler.py
mototli/server/protocol.py
mototli/server/router.py
mototli/server/server.py
mototli/utils/__init__.py
mototli/utils/downloads.py
mototli/utils/mime.py
mototli-0.1.1.dist-info/WHEEL
mototli-0.1.1.dist-info/entry_points.txt
mototli-0.1.1.dist-info/METADATA
mototli-0.1.1.dist-info/RECORD
