Metadata-Version: 2.3
Name: mototli
Version: 0.1.1
Summary: Modern Gopher protocol server and client implementation using asyncio
Keywords: gopher,protocol,server,client,asyncio,networking
Author: Alan Velasco
Author-email: Alan Velasco <alanvelasco.a@gmail.com>
License: MIT
Classifier: Development Status :: 3 - Alpha
Classifier: Intended Audience :: Developers
Classifier: License :: OSI Approved :: MIT License
Classifier: Programming Language :: Python :: 3
Classifier: Programming Language :: Python :: 3.10
Classifier: Programming Language :: Python :: 3.11
Classifier: Programming Language :: Python :: 3.12
Classifier: Programming Language :: Python :: 3.13
Classifier: Topic :: Internet
Classifier: Topic :: Software Development :: Libraries :: Python Modules
Classifier: Framework :: AsyncIO
Requires-Dist: rich>=14.2.0
Requires-Dist: structlog>=25.5.0
Requires-Dist: tomli>=2.0.0 ; python_full_version < '3.11'
Requires-Dist: typer>=0.20.0
Requires-Python: >=3.10
Project-URL: Bug Tracker, https://github.com/alanbato/mototli/issues
Project-URL: Documentation, https://mototli.readthedocs.io
Project-URL: Repository, https://github.com/alanbato/mototli
